Metadata-Version: 2.1
Name: AlexDistAlx
Version: 0.0
Summary: Gaussian and Binomial distributions
Home-page: UNKNOWN
Author-email: s.aleks-02@mail.ru
License: MIT
Platform: UNKNOWN
License-File: LICENSE.txt
